mseep_synapse_mcp-0.1.4.dist-info/licenses/LICENSE
synapse_mcp/__init__.py
synapse_mcp/__main__.py
synapse_mcp/auth.py
synapse_mcp/query.py
synapse_mcp/utils.py
synapse_mcp/entities/__init__.py
synapse_mcp/entities/base.py
synapse_mcp/entities/croissant.py
synapse_mcp/entities/dataset.py
synapse_mcp/entities/file.py
synapse_mcp/entities/folder.py
synapse_mcp/entities/project.py
synapse_mcp/entities/table.py
mseep_synapse_mcp-0.1.4.dist-info/METADATA
mseep_synapse_mcp-0.1.4.dist-info/WHEEL
mseep_synapse_mcp-0.1.4.dist-info/entry_points.txt
mseep_synapse_mcp-0.1.4.dist-info/top_level.txt
mseep_synapse_mcp-0.1.4.dist-info/RECORD
