Metadata-Version: 2.4
Name: mseep-synapse-mcp
Version: 0.1.4
Summary: A Model Context Protocol (MCP) server that exposes Synapse Entities with Croissant metadata support
Author-email: mseep <support@skydeck.ai>
License: MIT
Project-URL: Homepage, https://github.com/SageBionetworks/synapse-mcp
Project-URL: Issues, https://github.com/SageBionetworks/synapse-mcp/issues
Keywords: synapse,mcp,croissant,metadata,bioinformatics
Classifier: Development Status :: 4 - Beta
Classifier: Intended Audience :: Science/Research
Classifier: License :: OSI Approved :: MIT License
Classifier: Programming Language :: Python :: 3
Classifier: Programming Language :: Python :: 3.10
Classifier: Programming Language :: Python :: 3.11
Classifier: Topic :: Scientific/Engineering :: Bio-Informatics
Requires-Python: >=3.10
License-File: LICENSE
Requires-Dist: mcp[cli]>=1.3.0
Requires-Dist: requests>=2.32.3
Requires-Dist: synapseclient>=4.7.0
Requires-Dist: fastapi>=0.110.0
Requires-Dist: uvicorn>=0.27.0
Dynamic: license-file
